string_validator-0.1.7.dist-info/METADATA
string_validator-0.1.7.dist-info/WHEEL
string_validator-0.1.7.dist-info/license_files/LICENSE
string_validator/__init__.py
string_validator/string_validator.cpython-311-arm-linux-gnueabihf.so
string_validator-0.1.7.dist-info/RECORD
