Metadata-Version: 2.1
Name: string_validator
Version: 0.1.7
Classifier: Programming Language :: Rust
Classifier: Programming Language :: Python :: Implementation :: CPython
Classifier: Programming Language :: Python :: Implementation :: PyPy
License-File: LICENSE
Summary: A fast and correct Python string validator library
Keywords: string,validator,fast
Author-email: tropicbliss <tropicbliss@protonmail.com>
Requires-Python: >=3.7
Project-URL: Homepage, https://github.com/tropicbliss/stringvalidator
